datasette_query_history/__init__.py
datasette_query_history/static/datasette-query-history.css
datasette_query_history/static/datasette-query-history.js
datasette_query_history-0.2.3.dist-info/LICENSE
datasette_query_history-0.2.3.dist-info/METADATA
datasette_query_history-0.2.3.dist-info/WHEEL
datasette_query_history-0.2.3.dist-info/entry_points.txt
datasette_query_history-0.2.3.dist-info/top_level.txt
datasette_query_history-0.2.3.dist-info/RECORD
