Metadata-Version: 2.1
Name: datasette-query-history
Version: 0.2.3
Summary: Datasette plugin that keeps a list of the queries you've run and lets you rerun them.
Home-page: https://github.com/bretwalker/datasette-query-history
Author: Bret Walker
License: Apache License, Version 2.0
Project-URL: Issues, https://github.com/bretwalker/datasette-query-history/issues
Project-URL: CI, https://github.com/bretwalker/datasette-query-history/actions
Project-URL: Changelog, https://github.com/bretwalker/datasette-query-history/releases
Platform: UNKNOWN
Requires-Python: >=3.6
Requires-Dist: datasette
Provides-Extra: test
Requires-Dist: pytest ; extra == 'test'
Requires-Dist: pytest-asyncio ; extra == 'test'
